ignis/__init__.py
ignis/deploy/__init__.py
ignis/deploy/deploy.py
ignis/deploy/images.py
ignis/deploy/mesos.py
ignis/deploy/nomad.py
ignis/deploy/registry.py
ignis/deploy/registry_ui.py
ignis/deploy/submitter.py
ignis/deploy/utils.py
ignis/deploy/version.py
ignis/deploy/zookeeper.py
ignis/deploy/resources/__init__.py
ignis/deploy/resources/singularity/__init__.py
ignis/deploy/resources/singularity/config.yaml
ignis/deploy/resources/singularityce/__init__.py
ignis/deploy/resources/singularityce/build.def
ignis/deploy/resources/zookeeper/__init__.py
ignis/deploy/resources/zookeeper/configuration.xsl
ignis/deploy/resources/zookeeper/jaas.conf
ignis/deploy/resources/zookeeper/log4j.properties
ignis/deploy/resources/zookeeper/myid
ignis/deploy/resources/zookeeper/zoo.cfg
ignis/deploy/resources/zookeeper/zoo.cfg.dynamic
ignishpc-2.2.1.dist-info/LICENSE
ignishpc-2.2.1.dist-info/METADATA
ignishpc-2.2.1.dist-info/WHEEL
ignishpc-2.2.1.dist-info/entry_points.txt
ignishpc-2.2.1.dist-info/top_level.txt
ignishpc-2.2.1.dist-info/RECORD
