Metadata-Version: 2.1
Name: ignishpc
Version: 2.2.1
Summary: IgnisHPC Deploy
Home-page: https://github.com/ignishpc/deploy
Author: cesarpomar
Author-email: cesaralfredo.pineiro@usc.es
License: UNKNOWN
Platform: UNKNOWN
Classifier: Programming Language :: Python :: 3
Classifier: License :: OSI Approved :: GNU General Public License v3 (GPLv3)
Classifier: Operating System :: POSIX :: Linux 
License-File: LICENSE
Requires-Dist: docker (>=4.1.0)
Requires-Dist: python-hosts (>=1.0)
Requires-Dist: GitPython
